[
  {
    "file": "edu_2022_3000.json",
    "name": "2022년 교육부선정3000(내용수정)",
    "description": "2022년 교육부 지정 필수 영단어 3000개(내용수정)",
    "wordCount": 3000,
    "category": "교육부 기본어휘(2022년)"
  },
  {
    "file": "edu_2022_elementary_800.json",
    "name": "교육부 기본어휘 2022년 - 초등(800)",
    "description": "교육부 기본어휘 2022년 - 초등(800) 800개",
    "wordCount": 800,
    "category": "교육부 기본어휘(2022년)"
  },
  {
    "file": "edu_2022_middle_high_1800.json",
    "name": "교육부 기본어휘 2022년 - 중고(1800)",
    "description": "교육부 기본어휘 2022년 - 중고(1800) 1800개",
    "wordCount": 1800,
    "category": "교육부 기본어휘(2022년)"
  },
  {
    "file": "edu_2022_advanced_400.json",
    "name": "교육부 기본어휘 2022년 - 전문(400)",
    "description": "교육부 기본어휘 2022년 - 전문(400) 400개",
    "wordCount": 400,
    "category": "교육부 기본어휘(2022년)"
  },
  {
    "file": "daily_english_500.json",
    "name": "일상생활 필수 영단어 500",
    "description": "일상생활에서 자주 사용하는 필수 영단어 500개",
    "wordCount": 500,
    "category": "일상/실용"
  },
  {
    "file": "travel_english_300.json",
    "name": "여행 영어 300",
    "description": "해외여행에서 꼭 필요한 영단어 및 표현 300개",
    "wordCount": 300,
    "category": "일상/실용"
  },
  {
    "file": "business_english_500.json",
    "name": "비즈니스 영어 500",
    "description": "비즈니스 환경에서 필수적인 영단어 및 표현 500개",
    "wordCount": 497,
    "category": "일상/실용"
  },
  {
    "file": "sat_2000.json",
    "name": "수능 필수 영단어 2000",
    "description": "대학수학능력시험 필수 영단어 2000개",
    "wordCount": 2000,
    "category": "시험대비"
  },
  {
    "file": "toeic_2000.json",
    "name": "토익 필수 영단어 2000",
    "description": "TOEIC 시험 필수 영단어 2000개",
    "wordCount": 2000,
    "category": "시험대비"
  },
  {
    "file": "toefl_2000.json",
    "name": "토플 필수 영단어 2000",
    "description": "TOEFL 시험 필수 영단어 2000개",
    "wordCount": 2000,
    "category": "시험대비"
  },
  {
    "file": "ielts_2000.json",
    "name": "IELTS 필수 영단어 2000",
    "description": "IELTS 시험 대비 필수 영단어 2000개",
    "wordCount": 2000,
    "category": "시험대비"
  },
  {
    "file": "civil_service_1000.json",
    "name": "공무원 영어 필수 영단어 1000",
    "description": "공무원 시험 영어 과목 필수 영단어 1000개",
    "wordCount": 988,
    "category": "시험대비"
  },
  {
    "file": "transfer_exam_1000.json",
    "name": "편입 영어 필수 영단어 1000",
    "description": "대학 편입 시험 영어 필수 영단어 1000개",
    "wordCount": 986,
    "category": "시험대비"
  },
  {
    "file": "sentence_patterns_250.json",
    "name": "영어 문장 5형식 예문 250",
    "description": "1형식부터 5형식까지 각 50개씩, 총 250개의 샘플 예문 모음",
    "wordCount": 250,
    "category": "시험대비"
  },
  {
    "file": "articles_200.json",
    "name": "영어 관사 용법 예문 200",
    "description": "부정관사(a/an) 100개, 정관사(the) 100개로 관사 사용 이유를 설명하는 예문 모음",
    "wordCount": 200,
    "category": "시험대비"
  }
]
